{
  "_class": "group",
  "booleanOperation": 0,
  "clippingMaskMode": 0,
  "do_objectID": "F8459096-EB87-420F-8CE8-935149666786",
  "exportOptions": {
    "_class": "exportOptions",
    "exportFormats": [
    ],
    "includedLayerIds": [
    ],
    "layerOptions": 0,
    "shouldTrim": false
  },
  "frame": {
    "_class": "rect",
    "constrainProportions": false,
    "do_objectID": "1978D023-C810-41B0-8A00-F793E34854A2",
    "height": 173,
    "width": 764,
    "x": 0,
    "y": 0
  },
  "hasClickThrough": false,
  "hasClippingMask": false,
  "isFixedToViewport": false,
  "isFlippedHorizontal": false,
  "isFlippedVertical": false,
  "isLocked": false,
  "isVisible": true,
  "layerListExpandedType": 0,
  "layers": [
    {
      "class": "group",
      "id": "F28911DF-80C0-4416-9C96-10819AA9892B"
    }
  ],
  "name": "Group 15",
  "nameIsFixed": false,
  "resizingConstraint": 0,
  "resizingType": 0,
  "rotation": 0,
  "shouldBreakMaskChain": false,
  "style": {
    "_class": "style",
    "do_objectID": "39B47E39-7CEF-4F9D-98D8-C9111D21F760",
    "endMarkerType": 0,
    "miterLimit": 10,
    "shadows": [
      {
        "_class": "shadow",
        "blurRadius": 8,
        "color": {
          "_class": "color",
          "alpha": 0.25,
          "blue": 0.1607843137254902,
          "green": 0.1607843137254902,
          "red": 0.1607843137254902
        },
        "contextSettings": {
          "_class": "graphicsContextSettings",
          "blendMode": 0,
          "opacity": 1
        },
        "isEnabled": true,
        "offsetX": 0,
        "offsetY": 2,
        "spread": 0
      }
    ],
    "startMarkerType": 0,
    "windingRule": 1
  },
  "userInfo": {
    "com.invisionlabs.library": {
      "original-layer": {
        "originalID": "151091CB-2291-4F15-B6FB-4754A91408F6",
        "version": 1
      }
    }
  }
}